n2yo/__init__.py
n2yo/exceptions.py
n2yo/n2yo.py
n2yo/models/__init__.py
n2yo/models/search.py
n2yo_api_wrapper-0.0.2.dist-info/LICENSE.txt
n2yo_api_wrapper-0.0.2.dist-info/METADATA
n2yo_api_wrapper-0.0.2.dist-info/WHEEL
n2yo_api_wrapper-0.0.2.dist-info/top_level.txt
n2yo_api_wrapper-0.0.2.dist-info/RECORD
