Metadata-Version: 2.1
Name: n2yo-api-wrapper
Version: 0.0.2
Summary: Unofficial Wrapper for N2YO.com API
Home-page: https://github.com/g1ampy/n2yo-api-wrapper
Author: Giampy
Author-email: g1ampy@proton.me
License: MIT
Classifier: Development Status :: 4 - Beta
Classifier: Programming Language :: Python
Classifier: Operating System :: OS Independent
Classifier: Intended Audience :: Developers
Classifier: Topic :: Software Development :: Libraries :: Python Modules
Requires-Python: >=3.10
License-File: LICENSE.txt
Requires-Dist: requests
Requires-Dist: dacite
Requires-Dist: beautifulsoup4
